DrissionExtention/BrowerExtention.py
DrissionExtention/PageExtention.py
drissionextention-0.0.8.dist-info/METADATA
drissionextention-0.0.8.dist-info/WHEEL
drissionextention-0.0.8.dist-info/licenses/LICENSE
drissionextention-0.0.8.dist-info/RECORD
