Metadata-Version: 2.4
Name: DrissionExtention
Version: 0.0.8
Summary: Extension for DrissionPage
Author-email: MouseRider <pyu@bapi.eu.org>
License-File: LICENSE
Classifier: License :: OSI Approved :: MIT License
Classifier: Operating System :: OS Independent
Classifier: Programming Language :: Python :: 3
Requires-Python: >=3.8
Requires-Dist: drissionpage>=4.1.0.0b19
